pickitup/command_line.py
pickitup/picker.py
pickitup-1.0.dist-info/LICENSE.txt
pickitup-1.0.dist-info/METADATA
pickitup-1.0.dist-info/WHEEL
pickitup-1.0.dist-info/entry_points.txt
pickitup-1.0.dist-info/top_level.txt
pickitup-1.0.dist-info/RECORD
