Metadata-Version: 2.1
Name: pickitup
Version: 1.0
Summary: Organize files with one simple command
Home-page: http://github.com/dogonso/pickitup
Author: Dogukan Meral
Author-email: dogukan.meral@yahoo.com
License: MIT
Keywords: organize linux windows folder extension modification file size manager
Platform: UNKNOWN
Classifier: License :: OSI Approved :: MIT License
Classifier: Operating System :: Microsoft :: Windows
Classifier: Operating System :: POSIX :: Linux
Classifier: Programming Language :: Python :: 3.8
Classifier: Topic :: Desktop Environment :: File Managers
Classifier: Topic :: Utilities
